Ejercicio5/Ejerccio5.v
// EJERCICIO 5: ECUACIÓN S.O.P. - Gate Level Modelling
module gateLevel_1(input wire A_1, B_1, C_1, output wire S1_1);

  wire NB_1, NC_1, P1_1, P2_1, P3_1;

  not (NB_1, B_1);
  not (NC_1, C_1);
  
  and (P1_1, A_1, NB_1, NC_1);
  and (P2_1, A_1, NB_1, C_1);
  and (P3_1, A_1, B_1, C_1);
  
  or  (S1_1, P1_1, P2_1, P3_1);

endmodule

// EJERCICIO 5: ECUACIÓN P.O.S. - Gate Level Modelling
module gateLevel_2(input wire A_2, B_2, C_2, output wire P1_2);
	
  wire NA_2, NB_2, NC_2, S1_2, S2_2, S3_2, S4_2, S5_2;

  not (NA_2, A_2);
  not (NB_2, B_2);
  not (NC_2, C_2);
  
  or (S1_2, A_2, B_2, C_2);
  or (S2_2, A_2, B_2, NC_2);
  or (S3_2, A_2, NB_2, C_2);
  or (S4_2, A_2, NB_2, NC_2);
  or (S5_2, NA_2, NB_2, C_2);
  
  and (P1_2, S1_2, S2_2, S3_2, S4_2, S5_2);

endmodule

// EJERCICIO 5: ECUACIÓN SOLUCIÓN CON MAPA DE KARNAUGH - Gate Level Modelling
module gateLevel_3(input wire A_3, B_3, C_3, output wire S1_3);

  wire NB_3, P1_3, P2_3;

  not (NB_3, B_3);
  
  and (P1_3, A_3, C_3);
  and (P2_3, A_3, NB_3);
  
  or  (S1_3, P1_3, P2_3);

endmodule



// EJERCICIO 5: ECUACIÓN S.O.P. - Behavioral Modelling
module operadores_1(input wire A_1, B_1, C_1, output wire Y_1);

  assign Y_1 = (A_1 & ~B_1 & ~C_1) | (A_1 & ~B_1 & C_1) | (A_1 & B_1 & C_1);
endmodule

// EJERCICIO 5: ECUACIÓN P.O.S. - Behavioral Modelling
module operadores_2(input wire A_2, B_2, C_2, output wire Y_2);

  assign Y_2 = (A_2 | B_2 | C_2) & (A_2 | B_2 | ~C_2) & (A_2 | ~B_2 | C_2) & (A_2 | ~B_2 | ~C_2) & (~A_2 | ~B_2 | C_2);

endmodule

// EJERCICIO 5: ECUACIÓN SOLUCIÓN CON MAPA DE KARNAUGH - Behavioral Modelling
module operadores_3(input wire A_3, B_3, C_3, output wire Y_3);

  assign Y_3 = (A_3 & C_3) | (A_3 & ~B_3);

endmodule

Ejercicio5/Ejerccio5_tb.v
module testbench();

  reg p1_1, p2_1, p3_1, p1_2, p2_2, p3_2, p1_3, p2_3, p3_3,   p4_1, p5_1, p6_1, p4_2, p5_2, p6_2, p4_3, p5_3, p6_3;
  wire led1_1, led1_2, led1_3, led2_1, led2_2, led2_3;
  
  gateLevel_1   G1(p1_1, p2_1, p3_1, led1_1);
  gateLevel_2   G2(p1_2, p2_2, p3_2, led1_2);
  gateLevel_3   G3(p1_3, p2_3, p3_3, led1_3);
  
  operadores_1 OP1(p4_1, p5_1, p6_1, led2_1);
  operadores_2 OP2(p4_2, p5_2, p6_2, led2_2);
  operadores_3 OP3(p4_3, p5_3, p6_3, led2_3);

  initial begin
	$display("<<<<<<<<<<<<<<<<<<<<<<<<<<<<<<Gate Level Modelling>>>>>>>>>>>>>>>>>>>>>>>>>>>>>>");
	$display("");
	$display("EJERCICIO 5: ECUACION S.O.P.");
    $display("A B C | Y");
    $display("------|--");
    $monitor("%b %b %b | %b", p1_1, p2_1, p3_1, led1_1);
       p1_1 = 0; p2_1 = 0; p3_1 = 0;
    #1 p1_1 = 0; p2_1 = 0; p3_1 = 1;
    #1 p1_1 = 0; p2_1 = 1; p3_1 = 0;
    #1 p1_1 = 0; p2_1 = 1; p3_1 = 1;
    #1 p1_1 = 1; p2_1 = 0; p3_1 = 0;
    #1 p1_1 = 1; p2_1 = 0; p3_1 = 1;
    #1 p1_1 = 1; p2_1 = 1; p3_1 = 0;
    #1 p1_1 = 1; p2_1 = 1; p3_1 = 1;
	#1 $display("");
  end
  
  initial begin
    #10
	$display("EJERCICIO 5: ECUACION P.O.S.");
    $display("A B C | Y");
    $display("------|--");
    $monitor("%b %b %b | %b", p1_2, p2_2, p3_2, led1_2);
       p1_2 = 0; p2_2 = 0; p3_2 = 0;
    #1 p1_2 = 0; p2_2 = 0; p3_2 = 1;
    #1 p1_2 = 0; p2_2 = 1; p3_2 = 0;
    #1 p1_2 = 0; p2_2 = 1; p3_2 = 1;
    #1 p1_2 = 1; p2_2 = 0; p3_2 = 0;
    #1 p1_2 = 1; p2_2 = 0; p3_2 = 1;
    #1 p1_2 = 1; p2_2 = 1; p3_2 = 0;
    #1 p1_2 = 1; p2_2 = 1; p3_2 = 1;
	#1 $display("");
  end
  
  initial begin
    #20
	$display("EJERCICIO 5: ECUACION SOLUCION CON MAPA DE KARNAUGH");
    $display("A B C | Y");
    $display("------|--");
    $monitor("%b %b %b | %b", p1_3, p2_3, p3_3, led1_3);
       p1_3 = 0; p2_3 = 0; p3_3 = 0;
    #1 p1_3 = 0; p2_3 = 0; p3_3 = 1;
    #1 p1_3 = 0; p2_3 = 1; p3_3 = 0;
    #1 p1_3 = 0; p2_3 = 1; p3_3 = 1;
    #1 p1_3 = 1; p2_3 = 0; p3_3 = 0;
    #1 p1_3 = 1; p2_3 = 0; p3_3 = 1;
    #1 p1_3 = 1; p2_3 = 1; p3_3 = 0;
    #1 p1_3 = 1; p2_3 = 1; p3_3 = 1;
	#1 $display("");
  end
  

  initial begin
    #30
	$display("<<<<<<<<<<<<<<<<<<<<<<<<<<<<<<Behavioral Modelling>>>>>>>>>>>>>>>>>>>>>>>>>>>>>>");
	$display("");
	$display("EJERCICIO 5: ECUACION S.O.P.");
    $display("A B C | Y");
    $display("--------|--");
    $monitor("%b %b %b | %b", p4_1, p5_1, p6_1, led2_1);
       p4_1 = 0; p5_1 = 0; p6_1 = 0;
    #1 p4_1 = 0; p5_1 = 0; p6_1 = 1;
    #1 p4_1 = 0; p5_1 = 1; p6_1 = 0;
    #1 p4_1 = 0; p5_1 = 1; p6_1 = 1;
    #1 p4_1 = 1; p5_1 = 0; p6_1 = 0;
    #1 p4_1 = 1; p5_1 = 0; p6_1 = 1;
    #1 p4_1 = 1; p5_1 = 1; p6_1 = 0;
    #1 p4_1 = 1; p5_1 = 1; p6_1 = 1;
	#1 $display("");
	
  end
  
  initial begin
    #40
	$display("EJERCICIO 5: ECUACION P.O.S.");
    $display("A B C | Y");
    $display("--------|--");
    $monitor("%b %b %b | %b", p4_2, p5_2, p6_2, led2_2);
       p4_2 = 0; p5_2 = 0; p6_2 = 0;
    #1 p4_2 = 0; p5_2 = 0; p6_2 = 1;
    #1 p4_2 = 0; p5_2 = 1; p6_2 = 0;
    #1 p4_2 = 0; p5_2 = 1; p6_2 = 1;
    #1 p4_2 = 1; p5_2 = 0; p6_2 = 0;
    #1 p4_2 = 1; p5_2 = 0; p6_2 = 1;
    #1 p4_2 = 1; p5_2 = 1; p6_2 = 0;
    #1 p4_2 = 1; p5_2 = 1; p6_2 = 1;
	#1 $display("");
	
  end
  
  initial begin
    #50
	$display("EJERCICIO 5: ECUACION SOLUCION CON MAPA DE KARNAUGH");
    $display("A B C | Y");
    $display("--------|--");
    $monitor("%b %b %b | %b", p4_3, p5_3, p6_3, led2_3);
       p4_3 = 0; p5_3 = 0; p6_3 = 0;
    #1 p4_3 = 0; p5_3 = 0; p6_3 = 1;
    #1 p4_3 = 0; p5_3 = 1; p6_3 = 0;
    #1 p4_3 = 0; p5_3 = 1; p6_3 = 1;
    #1 p4_3 = 1; p5_3 = 0; p6_3 = 0;
    #1 p4_3 = 1; p5_3 = 0; p6_3 = 1;
    #1 p4_3 = 1; p5_3 = 1; p6_3 = 0;
    #1 p4_3 = 1; p5_3 = 1; p6_3 = 1;
	#1 $display("");
	
  end
  
 
  initial
    #60	$finish;
  
  initial begin
    $dumpfile("Ejerccio5_tb.vcd");
    $dumpvars(0, testbench);
  end
  
endmodule

Ejercicio5/Ejerccio5_tb.vcd
$date
	Fri Aug 07 17:33:43 2020
$end
$version
	Icarus Verilog
$end
$timescale
	1ps
$end
$scope module testbench $end
$var wire 1 ! led2_3 $end
$var wire 1 " led2_2 $end
$var wire 1 # led2_1 $end
$var wire 1 $ led1_3 $end
$var wire 1 % led1_2 $end
$var wire 1 & led1_1 $end
$var reg 1 ' p1_1 $end
$var reg 1 ( p1_2 $end
$var reg 1 ) p1_3 $end
$var reg 1 * p2_1 $end
$var reg 1 + p2_2 $end
$var reg 1 , p2_3 $end
$var reg 1 - p3_1 $end
$var reg 1 . p3_2 $end
$var reg 1 / p3_3 $end
$var reg 1 0 p4_1 $end
$var reg 1 1 p4_2 $end
$var reg 1 2 p4_3 $end
$var reg 1 3 p5_1 $end
$var reg 1 4 p5_2 $end
$var reg 1 5 p5_3 $end
$var reg 1 6 p6_1 $end
$var reg 1 7 p6_2 $end
$var reg 1 8 p6_3 $end
$scope module G1 $end
$var wire 1 ' A_1 $end
$var wire 1 * B_1 $end
$var wire 1 - C_1 $end
$var wire 1 9 NB_1 $end
$var wire 1 : NC_1 $end
$var wire 1 ; P1_1 $end
$var wire 1 < P2_1 $end
$var wire 1 = P3_1 $end
$var wire 1 & S1_1 $end
$upscope $end
$scope module G2 $end
$var wire 1 ( A_2 $end
$var wire 1 + B_2 $end
$var wire 1 . C_2 $end
$var wire 1 > NA_2 $end
$var wire 1 ? NB_2 $end
$var wire 1 @ NC_2 $end
$var wire 1 % P1_2 $end
$var wire 1 A S1_2 $end
$var wire 1 B S2_2 $end
$var wire 1 C S3_2 $end
$var wire 1 D S4_2 $end
$var wire 1 E S5_2 $end
$upscope $end
$scope module G3 $end
$var wire 1 ) A_3 $end
$var wire 1 , B_3 $end
$var wire 1 / C_3 $end
$var wire 1 F NB_3 $end
$var wire 1 G P1_3 $end
$var wire 1 H P2_3 $end
$var wire 1 $ S1_3 $end
$upscope $end
$scope module OP1 $end
$var wire 1 0 A_1 $end
$var wire 1 3 B_1 $end
$var wire 1 6 C_1 $end
$var wire 1 # Y_1 $end
$upscope $end
$scope module OP2 $end
$var wire 1 1 A_2 $end
$var wire 1 4 B_2 $end
$var wire 1 7 C_2 $end
$var wire 1 " Y_2 $end
$upscope $end
$scope module OP3 $end
$var wire 1 2 A_3 $end
$var wire 1 5 B_3 $end
$var wire 1 8 C_3 $end
$var wire 1 ! Y_3 $end
$upscope $end
$upscope $end
$enddefinitions $end
#0
$dumpvars
xH
xG
xF
xE
xD
xC
xB
xA
x@
x?
x>
0=
0<
0;
1:
19
x8
x7
x6
x5
x4
x3
x2
x1
x0
x/
x.
0-
x,
x+
0*
x)
x(
0'
0&
x%
x$
x#
x"
x!
$end
#1
0:
1-
#2
1:
09
0-
1*
#3
0:
1-
#4
1&
1;
1:
19
0-
0*
1'
#5
0;
0:
1<
1-
#6
0&
1:
0<
09
0-
1*
#7
1&
0:
1=
1-
#10
0%
1B
1C
1D
1@
1E
1?
1>
0A
0.
0+
0(
#11
0%
0B
0@
1A
1.
#12
1@
0C
0?
1B
0.
1+
#13
0%
0D
0@
1C
1.
#14
1%
1@
1?
0>
1D
0.
0+
1(
#15
0@
1.
#16
0%
1@
0E
0?
0.
1+
#17
1%
0@
1E
1.
#20
0$
1F
0G
0H
0/
0,
0)
#21
1/
#22
0F
0/
1,
#23
1/
#24
1$
1H
1F
0/
0,
1)
#25
1G
1/
#26
0$
0H
0G
0F
0/
1,
#27
1$
1G
1/
#30
0#
06
03
00
#31
16
#32
06
13
#33
16
#34
1#
06
03
10
#35
16
#36
0#
06
13
#37
1#
16
#40
0"
07
04
01
#41
17
#42
07
14
#43
17
#44
1"
07
04
11
#45
17
#46
0"
07
14
#47
1"
17
#50
0!
08
05
02
#51
18
#52
08
15
#53
18
#54
1!
08
05
12
#55
18
#56
0!
08
15
#57
1!
18
