Ejercicio4/Ejerccio4.v
// EJERCICIO #1: TABLA 1
module gateLevel_1(input wire A_1, B_1, C_1, output wire S1_1);

  wire NA_1, NB_1, NC_1, P1_1, P2_1, P3_1;

  not (NA_1, A_1);
  not (NB_1, B_1);
  not (NC_1, C_1);
  
  and (P1_1, NA_1, NC_1);
  and (P2_1, A_1, C_1);
  and (P3_1, A_1, NB_1);
  
  or  (S1_1, P1_1, P2_1, P3_1);

endmodule

// EJERCICIO #1: TABLA 2
module gateLevel_2(input wire A_2, B_2, C_2, output wire NB_2);

  not (NB_2, B_2);

endmodule

// EJERCICIO #2: TABLA 2
module gateLevel_3(input wire A_3, B_3, C_3, output wire S1_3);

  wire NB_3, NC_3;

  not (NB_3, B_3);
  
  or  (S1_3, NB_3, C_3);

endmodule

// EJERCICIO #2: TABLA 4
module gateLevel_4(input wire A_4, B_4, C_4, output wire S1_4);

  wire NA_4, NC_4, P1_4;

  not (NA_4, A_4);
  not (NC_4, C_4);
  
  and (P1_4, NA_4, NC_4);
  
  or  (S1_4, P1_4, B_4);

endmodule

// EJERCICIO #1: TABLA 3
module operadores_1(input wire A_1, B_1, C_1, D_1, output wire Y_1);

  assign Y_1 = (~A_1 & ~B_1 & ~C_1 & ~D_1) | (~A_1 & ~B_1 & C_1 & D_1) | (~A_1 & B_1 & ~C_1 & D_1) |(~A_1 & B_1 & C_1 & ~D_1) |(A_1 & B_1 & ~C_1 & ~D_1) |(A_1 & B_1 & C_1 & D_1) |(A_1 & ~B_1 & ~C_1 & D_1) |(A_1 & ~B_1 & C_1 & ~D_1);

endmodule

// EJERCICIO #1: TABLA 4
module operadores_2(input wire A_2, B_2, C_2, D_2, output wire Y_2);

  assign Y_2 = (B_2 & D_2) | (A_2 & ~D_2) | (A_2 & C_2);

endmodule

// EJERCICIO #2: TABLA 1
module operadores_3(input wire A_3, B_3, C_3, D_3, output wire Y_3);

  assign Y_3 = (A_3 & ~C_3) | (~B_3 & ~C_3 & ~D_3) | (A_3 & ~B_3) |(A_3 & C_3 & ~D_3);

endmodule

// EJERCICIO #2: TABLA 3
module operadores_4(input wire A_4, B_4, C_4, D_4, output wire Y_4);

  assign Y_4 = (~ B_4 & ~C_4 & D_4) | (A_4 & D_4) | (B_4);

endmodule

Ejercicio4/Ejerccio4_tb.v
module testbench();

  reg p1_1, p2_1, p3_1, p1_2, p2_2, p3_2, p1_3, p2_3, p3_3, p1_4, p2_4, p3_4,   p4_1, p5_1, p6_1, p7_1, p4_2, p5_2, p6_2, p7_2, p4_3, p5_3, p6_3, p7_3, p4_4, p5_4, p6_4, p7_4;
  wire led1_1, led1_2, led1_3, led1_4, led2_1, led2_2, led2_3, led2_4;

  gateLevel_1   G1(p1_1, p2_1, p3_1, led1_1);
  gateLevel_2   G2(p1_2, p2_2, p3_2, led1_2);
  gateLevel_3   G3(p1_3, p2_3, p3_3, led1_3);
  gateLevel_4   G4(p1_4, p2_4, p3_4, led1_4);
  
  operadores_1 OP1(p4_1, p5_1, p6_1, p7_1, led2_1);
  operadores_2 OP2(p4_2, p5_2, p6_2, p7_2, led2_2);
  operadores_3 OP3(p4_3, p5_3, p6_3, p7_3, led2_3);
  operadores_4 OP4(p4_4, p5_4, p6_4, p7_4, led2_4);

  initial begin
	$display("");
	$display("EJERCICIO 1: TABLA 1");
    $display("A B C | Y");
    $display("------|--");
    $monitor("%b %b %b | %b", p1_1, p2_1, p3_1, led1_1);
       p1_1 = 0; p2_1 = 0; p3_1 = 0;
    #1 p1_1 = 0; p2_1 = 0; p3_1 = 1;
    #1 p1_1 = 0; p2_1 = 1; p3_1 = 0;
    #1 p1_1 = 0; p2_1 = 1; p3_1 = 1;
    #1 p1_1 = 1; p2_1 = 0; p3_1 = 0;
    #1 p1_1 = 1; p2_1 = 0; p3_1 = 1;
    #1 p1_1 = 1; p2_1 = 1; p3_1 = 0;
    #1 p1_1 = 1; p2_1 = 1; p3_1 = 1;
	#1 $display("");
  end
  
  initial begin
    #10
	$display("EJERCICIO 1: TABLA 2");
    $display("A B C | Y");
    $display("------|--");
    $monitor("%b %b %b | %b", p1_2, p2_2, p3_2, led1_2);
       p1_2 = 0; p2_2 = 0; p3_2 = 0;
    #1 p1_2 = 0; p2_2 = 0; p3_2 = 1;
    #1 p1_2 = 0; p2_2 = 1; p3_2 = 0;
    #1 p1_2 = 0; p2_2 = 1; p3_2 = 1;
    #1 p1_2 = 1; p2_2 = 0; p3_2 = 0;
    #1 p1_2 = 1; p2_2 = 0; p3_2 = 1;
    #1 p1_2 = 1; p2_2 = 1; p3_2 = 0;
    #1 p1_2 = 1; p2_2 = 1; p3_2 = 1;
	#1 $display("");
  end
  
  initial begin
    #20
	$display("EJERCICIO 2: TABLA 2");
    $display("A B C | Y");
    $display("------|--");
    $monitor("%b %b %b | %b", p1_3, p2_3, p3_3, led1_3);
       p1_3 = 0; p2_3 = 0; p3_3 = 0;
    #1 p1_3 = 0; p2_3 = 0; p3_3 = 1;
    #1 p1_3 = 0; p2_3 = 1; p3_3 = 0;
    #1 p1_3 = 0; p2_3 = 1; p3_3 = 1;
    #1 p1_3 = 1; p2_3 = 0; p3_3 = 0;
    #1 p1_3 = 1; p2_3 = 0; p3_3 = 1;
    #1 p1_3 = 1; p2_3 = 1; p3_3 = 0;
    #1 p1_3 = 1; p2_3 = 1; p3_3 = 1;
	#1 $display("");
  end
  
  initial begin
    #30
	$display("EJERCICIO 2: TABLA 4");
    $display("A B C | Y");
    $display("------|--");
    $monitor("%b %b %b | %b", p1_4, p2_4, p3_4, led1_4);
       p1_4 = 0; p2_4 = 0; p3_4 = 0;
    #1 p1_4 = 0; p2_4 = 0; p3_4 = 1;
    #1 p1_4 = 0; p2_4 = 1; p3_4 = 0;
    #1 p1_4 = 0; p2_4 = 1; p3_4 = 1;
    #1 p1_4 = 1; p2_4 = 0; p3_4 = 0;
    #1 p1_4 = 1; p2_4 = 0; p3_4 = 1;
    #1 p1_4 = 1; p2_4 = 1; p3_4 = 0;
    #1 p1_4 = 1; p2_4 = 1; p3_4 = 1;
	#1 $display("");
	#1 $display("-.-.-.-.-.-.-.-.-.-.-.-.-.-.-.-.-.-.-.-.-.-.-.-.-.-.-.-.-.-.-.-.-.-.-.-.-.-.-.-.-.-.-.-.-.-.-.-.-.-.-.-.-.-.-.-.-.-.-.-");
  end
  
  initial begin
    #40
	$display("EJERCICIO 1: TABLA 3");
    $display("A B C D | Y");
    $display("--------|--");
    $monitor("%b %b %b %b | %b", p4_1, p5_1, p6_1, p7_1, led2_1);
       p4_1 = 0; p5_1 = 0; p6_1 = 0; p7_1 = 0;
    #1 p4_1 = 0; p5_1 = 0; p6_1 = 0; p7_1 = 1;
    #1 p4_1 = 0; p5_1 = 0; p6_1 = 1; p7_1 = 0;
    #1 p4_1 = 0; p5_1 = 0; p6_1 = 1; p7_1 = 1;
    #1 p4_1 = 0; p5_1 = 1; p6_1 = 0; p7_1 = 0;
    #1 p4_1 = 0; p5_1 = 1; p6_1 = 0; p7_1 = 1;
    #1 p4_1 = 0; p5_1 = 1; p6_1 = 1; p7_1 = 0;
    #1 p4_1 = 0; p5_1 = 1; p6_1 = 1; p7_1 = 1;
	#1 p4_1 = 1; p5_1 = 0; p6_1 = 0; p7_1 = 0;
    #1 p4_1 = 1; p5_1 = 0; p6_1 = 0; p7_1 = 1;
    #1 p4_1 = 1; p5_1 = 0; p6_1 = 1; p7_1 = 0;
    #1 p4_1 = 1; p5_1 = 0; p6_1 = 1; p7_1 = 1;
    #1 p4_1 = 1; p5_1 = 1; p6_1 = 0; p7_1 = 0;
    #1 p4_1 = 1; p5_1 = 1; p6_1 = 0; p7_1 = 1;
    #1 p4_1 = 1; p5_1 = 1; p6_1 = 1; p7_1 = 0;
    #1 p4_1 = 1; p5_1 = 1; p6_1 = 1; p7_1 = 1;
	#1 $display("");
	
  end
  
  initial begin
    #60
	$display("EJERCICIO 1: TABLA 4");
    $display("A B C D | Y");
    $display("--------|--");
    $monitor("%b %b %b %b | %b", p4_2, p5_2, p6_2, p7_2, led2_2);
       p4_2 = 0; p5_2 = 0; p6_2 = 0; p7_2 = 0;
    #1 p4_2 = 0; p5_2 = 0; p6_2 = 0; p7_2 = 1;
    #1 p4_2 = 0; p5_2 = 0; p6_2 = 1; p7_2 = 0;
    #1 p4_2 = 0; p5_2 = 0; p6_2 = 1; p7_2 = 1;
    #1 p4_2 = 0; p5_2 = 1; p6_2 = 0; p7_2 = 0;
    #1 p4_2 = 0; p5_2 = 1; p6_2 = 0; p7_2 = 1;
    #1 p4_2 = 0; p5_2 = 1; p6_2 = 1; p7_2 = 0;
    #1 p4_2 = 0; p5_2 = 1; p6_2 = 1; p7_2 = 1;
	#1 p4_2 = 1; p5_2 = 0; p6_2 = 0; p7_2 = 0;
    #1 p4_2 = 1; p5_2 = 0; p6_2 = 0; p7_2 = 1;
    #1 p4_2 = 1; p5_2 = 0; p6_2 = 1; p7_2 = 0;
    #1 p4_2 = 1; p5_2 = 0; p6_2 = 1; p7_2 = 1;
    #1 p4_2 = 1; p5_2 = 1; p6_2 = 0; p7_2 = 0;
    #1 p4_2 = 1; p5_2 = 1; p6_2 = 0; p7_2 = 1;
    #1 p4_2 = 1; p5_2 = 1; p6_2 = 1; p7_2 = 0;
    #1 p4_2 = 1; p5_2 = 1; p6_2 = 1; p7_2 = 1;
	#1 $display("");
	
  end
  
  initial begin
    #80
	$display("EJERCICIO 2: TABLA 1");
    $display("A B C D | Y");
    $display("--------|--");
    $monitor("%b %b %b %b | %b", p4_3, p5_3, p6_3, p7_3, led2_3);
       p4_3 = 0; p5_3 = 0; p6_3 = 0; p7_3 = 0;
    #1 p4_3 = 0; p5_3 = 0; p6_3 = 0; p7_3 = 1;
    #1 p4_3 = 0; p5_3 = 0; p6_3 = 1; p7_3 = 0;
    #1 p4_3 = 0; p5_3 = 0; p6_3 = 1; p7_3 = 1;
    #1 p4_3 = 0; p5_3 = 1; p6_3 = 0; p7_3 = 0;
    #1 p4_3 = 0; p5_3 = 1; p6_3 = 0; p7_3 = 1;
    #1 p4_3 = 0; p5_3 = 1; p6_3 = 1; p7_3 = 0;
    #1 p4_3 = 0; p5_3 = 1; p6_3 = 1; p7_3 = 1;
	#1 p4_3 = 1; p5_3 = 0; p6_3 = 0; p7_3 = 0;
    #1 p4_3 = 1; p5_3 = 0; p6_3 = 0; p7_3 = 1;
    #1 p4_3 = 1; p5_3 = 0; p6_3 = 1; p7_3 = 0;
    #1 p4_3 = 1; p5_3 = 0; p6_3 = 1; p7_3 = 1;
    #1 p4_3 = 1; p5_3 = 1; p6_3 = 0; p7_3 = 0;
    #1 p4_3 = 1; p5_3 = 1; p6_3 = 0; p7_3 = 1;
    #1 p4_3 = 1; p5_3 = 1; p6_3 = 1; p7_3 = 0;
    #1 p4_3 = 1; p5_3 = 1; p6_3 = 1; p7_3 = 1;
	#1 $display("");
	
  end
  
  initial begin
    #100
	$display("EJERCICIO 2: TABLA 3");
    $display("A B C D | Y");
    $display("--------|--");
    $monitor("%b %b %b %b | %b", p4_4, p5_4, p6_4, p7_4, led2_4);
       p4_4 = 0; p5_4 = 0; p6_4 = 0; p7_4 = 0;
    #1 p4_4 = 0; p5_4 = 0; p6_4 = 0; p7_4 = 1;
    #1 p4_4 = 0; p5_4 = 0; p6_4 = 1; p7_4 = 0;
    #1 p4_4 = 0; p5_4 = 0; p6_4 = 1; p7_4 = 1;
    #1 p4_4 = 0; p5_4 = 1; p6_4 = 0; p7_4 = 0;
    #1 p4_4 = 0; p5_4 = 1; p6_4 = 0; p7_4 = 1;
    #1 p4_4 = 0; p5_4 = 1; p6_4 = 1; p7_4 = 0;
    #1 p4_4 = 0; p5_4 = 1; p6_4 = 1; p7_4 = 1;
	#1 p4_4 = 1; p5_4 = 0; p6_4 = 0; p7_4 = 0;
    #1 p4_4 = 1; p5_4 = 0; p6_4 = 0; p7_4 = 1;
    #1 p4_4 = 1; p5_4 = 0; p6_4 = 1; p7_4 = 0;
    #1 p4_4 = 1; p5_4 = 0; p6_4 = 1; p7_4 = 1;
    #1 p4_4 = 1; p5_4 = 1; p6_4 = 0; p7_4 = 0;
    #1 p4_4 = 1; p5_4 = 1; p6_4 = 0; p7_4 = 1;
    #1 p4_4 = 1; p5_4 = 1; p6_4 = 1; p7_4 = 0;
    #1 p4_4 = 1; p5_4 = 1; p6_4 = 1; p7_4 = 1;
	#1 $display("");

  end
  
  initial
    #120	$finish;
  
  initial begin
    $dumpfile("Ejerccio4_tb.vcd");
    $dumpvars(0, testbench);
  end
  
endmodule

Ejercicio4/Ejerccio4_tb.vcd
$date
	Fri Aug 07 16:04:48 2020
$end
$version
	Icarus Verilog
$end
$timescale
	1ps
$end
$scope module testbench $end
$var wire 1 ! led2_4 $end
$var wire 1 " led2_3 $end
$var wire 1 # led2_2 $end
$var wire 1 $ led2_1 $end
$var wire 1 % led1_4 $end
$var wire 1 & led1_3 $end
$var wire 1 ' led1_2 $end
$var wire 1 ( led1_1 $end
$var reg 1 ) p1_1 $end
$var reg 1 * p1_2 $end
$var reg 1 + p1_3 $end
$var reg 1 , p1_4 $end
$var reg 1 - p2_1 $end
$var reg 1 . p2_2 $end
$var reg 1 / p2_3 $end
$var reg 1 0 p2_4 $end
$var reg 1 1 p3_1 $end
$var reg 1 2 p3_2 $end
$var reg 1 3 p3_3 $end
$var reg 1 4 p3_4 $end
$var reg 1 5 p4_1 $end
$var reg 1 6 p4_2 $end
$var reg 1 7 p4_3 $end
$var reg 1 8 p4_4 $end
$var reg 1 9 p5_1 $end
$var reg 1 : p5_2 $end
$var reg 1 ; p5_3 $end
$var reg 1 < p5_4 $end
$var reg 1 = p6_1 $end
$var reg 1 > p6_2 $end
$var reg 1 ? p6_3 $end
$var reg 1 @ p6_4 $end
$var reg 1 A p7_1 $end
$var reg 1 B p7_2 $end
$var reg 1 C p7_3 $end
$var reg 1 D p7_4 $end
$scope module G1 $end
$var wire 1 ) A_1 $end
$var wire 1 - B_1 $end
$var wire 1 1 C_1 $end
$var wire 1 E NA_1 $end
$var wire 1 F NB_1 $end
$var wire 1 G NC_1 $end
$var wire 1 H P1_1 $end
$var wire 1 I P2_1 $end
$var wire 1 J P3_1 $end
$var wire 1 ( S1_1 $end
$upscope $end
$scope module G2 $end
$var wire 1 * A_2 $end
$var wire 1 . B_2 $end
$var wire 1 2 C_2 $end
$var wire 1 ' NB_2 $end
$upscope $end
$scope module G3 $end
$var wire 1 + A_3 $end
$var wire 1 / B_3 $end
$var wire 1 3 C_3 $end
$var wire 1 K NB_3 $end
$var wire 1 & S1_3 $end
$upscope $end
$scope module G4 $end
$var wire 1 , A_4 $end
$var wire 1 0 B_4 $end
$var wire 1 4 C_4 $end
$var wire 1 L NA_4 $end
$var wire 1 M NC_4 $end
$var wire 1 N P1_4 $end
$var wire 1 % S1_4 $end
$upscope $end
$scope module OP1 $end
$var wire 1 5 A_1 $end
$var wire 1 9 B_1 $end
$var wire 1 = C_1 $end
$var wire 1 A D_1 $end
$var wire 1 $ Y_1 $end
$upscope $end
$scope module OP2 $end
$var wire 1 6 A_2 $end
$var wire 1 : B_2 $end
$var wire 1 > C_2 $end
$var wire 1 B D_2 $end
$var wire 1 # Y_2 $end
$upscope $end
$scope module OP3 $end
$var wire 1 7 A_3 $end
$var wire 1 ; B_3 $end
$var wire 1 ? C_3 $end
$var wire 1 C D_3 $end
$var wire 1 " Y_3 $end
$upscope $end
$scope module OP4 $end
$var wire 1 8 A_4 $end
$var wire 1 < B_4 $end
$var wire 1 @ C_4 $end
$var wire 1 D D_4 $end
$var wire 1 ! Y_4 $end
$upscope $end
$upscope $end
$enddefinitions $end
#0
$dumpvars
xN
xM
xL
xK
0J
0I
1H
1G
1F
1E
xD
xC
xB
xA
x@
x?
x>
x=
x<
x;
x:
x9
x8
x7
x6
x5
x4
x3
x2
01
x0
x/
x.
0-
x,
x+
x*
0)
1(
x'
x&
x%
x$
x#
x"
x!
$end
#1
0(
0H
0G
11
#2
1(
1H
1G
0F
01
1-
#3
0(
0H
0G
11
#4
1(
1J
1G
1F
0E
01
0-
1)
#5
0G
1I
11
#6
0(
0J
1G
0I
0F
01
1-
#7
1(
0G
1I
11
#10
1'
02
0.
0*
#11
12
#12
0'
02
1.
#13
12
#14
1'
02
0.
1*
#15
12
#16
0'
02
1.
#17
12
#20
1&
1K
03
0/
0+
#21
13
#22
0&
0K
03
1/
#23
1&
13
#24
1K
03
0/
1+
#25
13
#26
0&
0K
03
1/
#27
1&
13
#30
1%
1N
1M
1L
04
00
0,
#31
0%
0N
0M
14
#32
1N
1M
1%
04
10
#33
0N
0M
14
#34
1M
0%
0L
04
00
1,
#35
0M
14
#36
1M
1%
04
10
#37
0M
14
#40
1$
0A
0=
09
05
#41
0$
1A
#42
0A
1=
#43
1$
1A
#44
0$
0A
0=
19
#45
1$
1A
#46
0A
1=
#47
0$
1A
#48
0A
0=
09
15
#49
1$
1A
#50
0A
1=
#51
0$
1A
#52
1$
0A
0=
19
#53
0$
1A
#54
0A
1=
#55
1$
1A
#60
0#
0B
0>
0:
06
#61
1B
#62
0B
1>
#63
1B
#64
0B
0>
1:
#65
1#
1B
#66
0#
0B
1>
#67
1#
1B
#68
1#
0B
0>
0:
16
#69
0#
1B
#70
1#
0B
1>
#71
1B
#72
1#
0B
0>
1:
#73
1B
#74
0B
1>
#75
1B
#80
1"
0C
0?
0;
07
#81
0"
1C
#82
0C
1?
#83
1C
#84
0C
0?
1;
#85
1C
#86
0C
1?
#87
1C
#88
1"
0C
0?
0;
17
#89
1C
#90
0C
1?
#91
1C
#92
1"
0C
0?
1;
#93
1C
#94
0C
1?
#95
0"
1C
#100
0!
0D
0@
0<
08
#101
1!
1D
#102
0!
0D
1@
#103
1D
#104
1!
0D
0@
1<
#105
1D
#106
0D
1@
#107
1D
#108
0!
0D
0@
0<
18
#109
1!
1D
#110
0!
0D
1@
#111
1!
1D
#112
0D
0@
1<
#113
1D
#114
0D
1@
#115
1D
